README
setup.py
readability/__init__.py
readability/cleaners.py
readability/debug.py
readability/encoding.py
readability/htmls.py
readability/readability.py
readability_dig.egg-info/PKG-INFO
readability_dig.egg-info/SOURCES.txt
readability_dig.egg-info/dependency_links.txt
readability_dig.egg-info/requires.txt
readability_dig.egg-info/top_level.txt