Metadata-Version: 1.1
Name: readability-dig
Version: 0.4
Summary: Modified arc90's scraping hub port readability tool for dig data
Home-page: https://github.com/muthurajendran/python-readability-dig
Author: Muthu Rajendran R G
Author-email: muthurajendranrg@gmail.com
License: Apache License 2.0
Download-URL: https://github.com/muthurajendran/python-readability-dig/tarball/0.1
Platform: UNKNOWN
Classifier: Environment :: Web Environment
Classifier: Intended Audience :: Developers
Classifier: Operating System :: OS Independent
Classifier: Programming Language :: Python
